haoutils/__init__.py
haoutils/excel/__init__.py
haoutils/excel/excel.py
haoutils/haotime/__init__.py
haoutils/haotime/haotime.py
haoutils/ssh/__init__.py
haoutils/ssh/ssh.py
haoutils-0.3.dist-info/METADATA
haoutils-0.3.dist-info/WHEEL
haoutils-0.3.dist-info/top_level.txt
haoutils-0.3.dist-info/RECORD
