Metadata-Version: 2.1
Name: haoutils
Version: 0.3
Summary: UNKNOWN
Home-page: https://github.com/haoqihan/haoutils
Author: haoqihan
Author-email: 2263310007@qq.com
License: MIT Licence
Platform: window10
Platform: Linux
Classifier: Programming Language :: Python :: 3.6
Classifier: Programming Language :: Python :: 3.7
Classifier: License :: OSI Approved :: MIT License
Classifier: Operating System :: OS Independent
Requires-Dist: paramiko
Requires-Dist: openpyxl
